sureberus/__init__.py
sureberus/constants.py
sureberus/errors.py
sureberus/schema.py
sureberus-0.15.0.dist-info/METADATA
sureberus-0.15.0.dist-info/WHEEL
sureberus-0.15.0.dist-info/top_level.txt
sureberus-0.15.0.dist-info/RECORD
