Metadata-Version: 2.1
Name: sureberus
Version: 0.15.0
Summary: Validation & transformation.
Home-page: UNKNOWN
Author: Christopher Armstrong
License: MIT
Project-URL: Source Code, https://github.com/radix/sureberus/
Project-URL: Documentation, https://radix.github.io/sureberus/
Platform: UNKNOWN
Classifier: License :: OSI Approved :: MIT License
Classifier: Programming Language :: Python :: 2
Classifier: Programming Language :: Python :: 3
Requires-Dist: attrs
Requires-Dist: six
